<source>
<publisher>Cookorico</publisher>
<publisherurl>https://www.cookorico.com</publisherurl>
<lastupdatedat>2025-07-19 09:00</lastupdatedat>

<job>
  <company>Hively Hospitality - Thalazur</company>
  <companydescription/>
  <companyuuid>5</companyuuid>
  <logotype></logotype>
  <headquarters>
    <country></country>
    <city></city>
    <postalcode></postalcode>
    <zip></zip>
    <address></address>
    <countrycode></countrycode>
    <region/>
  </headquarters>
  <referencenumber>8rqt3e</referencenumber>
  <jobboardid>cookorico</jobboardid>
  <title>Assistant(e) commercial(e)</title>
<description><![CDATA[
<p><strong>Notre site : THALAZUR Port Camargue</strong></p><p><br></p><p><strong>Dans le cadre d'un remplacement pour congés maternité, nous recrutons une ou un responsable commercial (e)</strong></p><p><br></p><p><strong>Votre mission :</strong></p><p>Organiser un séjour inoubliable à nos clients ! Au quotidien, il s’agira de :</p><ul><li>Commercialiser le site dans son intégralité&nbsp;: Hôtel, restaurant et centre de thalassothérapie</li><li>Porter l’image de l’établissement en suivant la stratégie commerciale et gérer la e-réputation</li><li>Gérer les demandes entrantes d'évènements ,séminaires</li><li>Contrôle matériel et état des salons</li><li>Assurer le suivi opérationnel des manifestations (séminaires, banquets…) en travaillant en direct avec les services annexes de l’établissement (cuisine, restaurant, réception, étages) , </li><li>Etablissement de devis , facturations des prestations</li><li>Développer et de fidéliser le portefeuille clients (présence sur le terrain, courts déplacements, visites de prospection, 1 a 2 salons dans l'année)</li><li>Organiser prospection téléphonique</li></ul><p><br></p><p><strong>Nous vous proposons :</strong></p><ul><li>Temps de travail de 39h par semaine avec 2 jours de repos consécutifs</li><li>Un 13ème mois dès 3 mois d'ancienneté et payable mensuellement par avance, un Plan d’Epargne Entreprise avec abondement, des avantages nourriture et chaque heure supplémentaire travaillée est comptabilisée en donnant droit à des repos en plus!</li><li>Des tarifs préférentiels dans notre réseau d’établissements</li><li>Mutuelle et Prévoyance offrant des garanties et une couverture maximales</li><li>Adhésion à une plateforme web avec réductions sur des produits du quotidien (cinéma, parcs d’attraction, courses alimentaires, salles de sport…</li><li>Réunion métier avec les commerciaux des 9 sites Thalazur et échanges régulier via visio conférence</li></ul> <p><strong>Votre profil :</strong></p><ul><li>Vous êtes diplômé d'une école hôtelière, de tourisme ou de commerce (Bac +2 ou Bac +3)</li><li>Vous avez validé une expérience similaire dans un établissement de même catégorie</li><li>Véritable développeur commercial, vous êtes tourné vers la satisfaction clients et les résultats</li><li>Vous êtes à l'aise avec les outils informatiques et logiciel</li><li>Vous êtes force de proposition, dynamique, rigoureux, organisé et autonome, vous avez un excellent relationnel</li><li>Vous avez une bonne maîtrise de l’anglais&nbsp;</li></ul><p><br></p><p>Nous faisons partie de HIVELY HOSPITALITY. Avec une quinzaine de marques à forte notoriété, 80 établissements en France et en Europe, et 60 métiers dans l’hôtellerie, la restauration et le bien-être, HIVELY HOSPITALITY offre une diversité d’opportunités et d’évolutions à toutes celles et ceux qui sont en quête de réalisation de soi. Un seul prérequis de départ : l’envie !&nbsp;</p><p><br></p><p> </p>]]></description>
  <startdate>2025-09-15</startdate>
  <enddate></enddate>
  <createddate>2025-07-18</createddate>
  <remotestatus></remotestatus>
  <employmenttype></employmenttype>
  <employmentlevel></employmentlevel>
  <url>https://hively-hospitality.talentview.io/jobs/8rqt3e?source=cookorico</url>
  <applyurl>https://hively-hospitality.talentview.io/jobs/8rqt3e?source=cookorico</applyurl>
  <coverimageurl></coverimageurl>
  <pitch></pitch>
  <applybuttontext/>
  <locations>
    <location>
      <country>France</country>
      <city>Le Grau-du-Roi</city>
      <zip>30240</zip>
      <address>227 Route des Marines</address>
      <countrycode>FR</countrycode>
      <region/>
    </location>
  </locations>
  <customfields/>
  <department>
    <name></name>
  </department>
  <role>
    <name/>
  </role>
  <recruiter>
    <name></name>
    <email></email>
    <phone></phone>
  </recruiter>
  <tags/>
  <salary>
    <min></min>
    <max></max>
    <currency></currency>
    <timeunit></timeunit>
  </salary>
</job>

</source>